README.rst
setup.py
mixcloud/__init__.py
mixcloud/client.py
mixcloud/tests.py
mixcloud/utils.py
mixcloud_python.egg-info/PKG-INFO
mixcloud_python.egg-info/SOURCES.txt
mixcloud_python.egg-info/dependency_links.txt
mixcloud_python.egg-info/pbr.json
mixcloud_python.egg-info/requires.txt
mixcloud_python.egg-info/top_level.txt