Metadata-Version: 1.1
Name: mixcloud-python
Version: 0.2
Summary: A Python wrapper around the Mixcloud API
Home-page: https://github.com/Said007/mixcloud-python
Author: Said Ali
Author-email: said.ali@msn.com
License: UNKNOWN
Platform: UNKNOWN
Classifier: Programming Language :: Python :: 2.7
Classifier: Programming Language :: Python :: 3
Classifier: Programming Language :: Python :: 3.4
Classifier: Programming Language :: Python :: 3.5
